sportrefpy/__init__.py
sportrefpy/assets/__init__.py
sportrefpy/assets/mlb_players.txt
sportrefpy/assets/nba_players.txt
sportrefpy/assets/nhl_players.txt
sportrefpy/cbb/__init__.py
sportrefpy/cbb/cbb.py
sportrefpy/cfb/__init__.py
sportrefpy/cfb/cfb.py
sportrefpy/errors/__init__.py
sportrefpy/errors/not_found.py
sportrefpy/mlb/__init__.py
sportrefpy/mlb/analysis.py
sportrefpy/mlb/helpers.py
sportrefpy/mlb/league.py
sportrefpy/mlb/player.py
sportrefpy/mlb/team.py
sportrefpy/nba/__init__.py
sportrefpy/nba/analysis.py
sportrefpy/nba/helpers.py
sportrefpy/nba/league.py
sportrefpy/nba/player.py
sportrefpy/nba/team.py
sportrefpy/nfl/__init__.py
sportrefpy/nfl/league.py
sportrefpy/nfl/team.py
sportrefpy/nhl/__init__.py
sportrefpy/nhl/analysis.py
sportrefpy/nhl/helpers.py
sportrefpy/nhl/league.py
sportrefpy/nhl/player.py
sportrefpy/nhl/team.py
tests/__init__.py
tests/coach_test.py
tests/league_test.py
tests/player_test.py
tests/team_test.py
sportrefpy-0.3.0.dist-info/LICENSE
sportrefpy-0.3.0.dist-info/METADATA
sportrefpy-0.3.0.dist-info/WHEEL
sportrefpy-0.3.0.dist-info/top_level.txt
sportrefpy-0.3.0.dist-info/RECORD
