Metadata-Version: 2.1
Name: sportrefpy
Version: 0.3.0
Summary: Python package to pull sports stats from all major sports leagues.
Home-page: https://github.com/alexkahan/sportrefpy
Author: alex kahan
Author-email: kahanscious@gmail.com
License: MIT
Keywords: sports reference stats nba nfl mlb cfb cbb
Platform: UNKNOWN
Classifier: Programming Language :: Python :: 3
Requires-Dist: beautifulsoup4 (>=4.10.0)
Requires-Dist: lxml (>=4.8.0)
Requires-Dist: numpy (>=1.22.3)
Requires-Dist: pandas (>=1.4.1)
Requires-Dist: pytest (>=7.1.1)
Requires-Dist: requests (>=2.27.1)
Requires-Dist: urllib3 (>=1.26.9)
Requires-Dist: pyenchant (>=3.2.2)
Requires-Dist: html5lib (>=1.1)
